petrelpy/__init__.py
petrelpy/__main__.py
petrelpy/cli.py
petrelpy/gslib.py
petrelpy/petrel.py
petrelpy/wellconnection.py
petrelpy-0.2.0.dist-info/METADATA
petrelpy-0.2.0.dist-info/WHEEL
petrelpy-0.2.0.dist-info/entry_points.txt
petrelpy-0.2.0.dist-info/licenses/LICENSE
petrelpy-0.2.0.dist-info/RECORD
