Metadata-Version: 2.4
Name: petrelpy
Version: 0.2.0
Summary: Utilities for working with Petrel imports and exports.
Author-email: Frank Male <frank.male@psu.edu>
License: Copyright 2018-2023 Frank Male
License-File: LICENSE
Requires-Python: >=3.9
Requires-Dist: click
Requires-Dist: dask[dataframe,diagnostics]
Requires-Dist: fastparquet
Requires-Dist: numpy
Requires-Dist: openpyxl
Requires-Dist: pandas
Requires-Dist: scipy
Requires-Dist: trogon
Provides-Extra: dev
Requires-Dist: ipykernel>=6.0.0; extra == 'dev'
Provides-Extra: docs
Requires-Dist: furo; extra == 'docs'
Requires-Dist: jupytext>=1.14; extra == 'docs'
Requires-Dist: myst-nb>=0.13.1; extra == 'docs'
Requires-Dist: myst-parser; extra == 'docs'
Requires-Dist: sphinx-autoapi>=1.8.4; extra == 'docs'
Requires-Dist: sphinx-copybutton; extra == 'docs'
Requires-Dist: sphinx-design; extra == 'docs'
Requires-Dist: sphinx-external-toc; extra == 'docs'
Requires-Dist: sphinx-sitemap; extra == 'docs'
Requires-Dist: sphinx>=5.0.2; extra == 'docs'
Provides-Extra: test
Requires-Dist: pytest-cov>=2.12.1; extra == 'test'
Requires-Dist: pytest-mpl>=0.16; extra == 'test'
Requires-Dist: pytest-xdist>=2.4; extra == 'test'
Requires-Dist: pytest>=6.2; extra == 'test'
